{
    "chapters":{
        "1":{
            "author_id":"tarandgreg",
            "author_name":"dude",
            "choices":[
                "movie character",
                "book character",
                "anime character",
                "video game character",
                "other"
            ],
            "content":"<div class=\"\"><div> <span>Your name is John and you had just discovered the ability to possess any fictional character by looking at said character through any medium. It could be a book and reading the description provided or simply looking at a picture or accurate drawing and simply willing for the possession to begin. The best part about this ability is that everything about this being you possess is at your disposal. Personality, body, finances, smarts, all of it was at your fingertips. Another fascinating thing was that if you ever got bored of your life, you could leave back to your original body and do it again.<br>\r\n<br>\r\nSince your first day of college started in thirty minutes, you begin to have cold feet. Why should i go to college when i can become anyone in an alternate reality. Moving over to your computer/bookshelf you browse before selecting?<br>\r\n<br>\r\n<br>\r\nWho do you become</span></div></div>",
            "created":1607497320,
            "id":2954070,
            "title":"Change of scenery "
        },
        "11":{
            "author_id":"tarandgreg",
            "author_name":"dude",
            "choices":[
                "superhero",
                "action",
                "adventure",
                "romance",
                "sci-fi"
            ],
            "content":"<div class=\"\"><span style=\"font-size:1.47em;\"><div> <span>Open your streaming service, you choose to watch a ________ movie<br>\r\n<br>\r\nsuperhero<br>\r\n<br>\r\naction<br>\r\n<br>\r\nadventure <br>\r\n<br>\r\nromance<br>\r\n<br>\r\nsci-fi</span></div></span></div>",
            "created":1607497500,
            "id":2954071,
            "title":"movie character"
        },
        "12":{
            "author_id":"tarandgreg",
            "author_name":"dude",
            "choices":[
                "fantasy",
                "action",
                "romance",
                "sci-fi",
                "other"
            ],
            "content":"<div class=\"\"><span style=\"font-size:1.47em;\"><div> <span>What genre</span></div></span></div>",
            "created":1607498340,
            "id":2954078,
            "title":"book character"
        },
        "13":{
            "author_id":"tarandgreg",
            "author_name":"dude",
            "choices":[
                "One piece (before timeskip)",
                "Bleach",
                "Naruto (any character)",
                "Dragon Ball Z (any character)",
                "other"
            ],
            "content":"<div class=\"\"><span style=\"font-size:1.47em;\"><div> <span>any of the big four?</span></div></span></div>",
            "created":1607497860,
            "id":2954074,
            "title":"anime character"
        },
        "131":{
            "author_id":"tarandgreg",
            "author_name":"dude",
            "choices":[
                "male",
                "female",
                "animal"
            ],
            "content":"<div class=\"\"><span style=\"font-size:1.47em;\"><div> <span>Turning your computer to Youtube, You decide to watch your favorite anime One Piece pre-time skip. Deciding it would be fun to live in an anime version of water world, you decide to possess_______</span></div></span></div>",
            "created":1607498760,
            "id":2954083,
            "title":"One piece (before timeskip)"
        },
        "1313":{
            "author_id":"tarandgreg",
            "author_name":"dude",
            "choices":[
                "sea king",
                "cotton candy chopper",
                "other"
            ],
            "content":"<div class=\"\"><span style=\"font-size:1.47em;\"><div> <span>Obviously you are going to choose a sea king right? right?</span></div></span></div>",
            "created":1607498880,
            "id":2954084,
            "title":"animal"
        },
        "13131":{
            "author_id":"tarandgreg",
            "author_name":"dude",
            "choices":[
                "small",
                "medium",
                "large"
            ],
            "content":"<div class=\"\"><span style=\"font-size:1.47em;\"><div> <span>Last option chaper<br>\r\n<br>\r\nsmall 200-999 ft <br>\r\n<br>\r\nmedium 1000-2000 ft <br>\r\n<br>\r\nlarge 2000+ ft (start in calm belt)</span></div></span></div>",
            "created":1607499000,
            "id":2954087,
            "title":"sea king"
        },
        "131313":{
            "author_id":"tarandgreg",
            "author_name":"dude",
            "choices":[
                "learning Haki",
                "time skip one year",
                "getting bored and starting over"
            ],
            "content":"<div class=\"\"><div> <span>Deciding that the life of a sea leviathan would be better than a dead end job and college, you will yourself into the body of the black and white sea beast from episode 55. Coming up out of the water, now in possession of your new body, you spot the Going Merry on the bridge of your nose. Smiling to yourself at your new possibilities you tilt your head forward dropping the ship as you slide back underwater, your massive body easily responding to your demands as you swim away. Deciding that since you are the largest sea king that the one piece universe created before they decided that another beast of your massive proportions was ridiculous, you knew the sea was safely yours. You also knew that there were a few who could challenge you, such as White Beard and Dracule Mihawk (Hawk Eyes). Not wanting to find your new self sliced in half you disappear under the waves to learn Haki. Besides what would be the Point of messing with people if they killed you before you could do so.</span></div></div>",
            "created":1607499900,
            "id":2954095,
            "title":"large"
        },
        "1313132":{
            "author_id":"tarandgreg",
            "author_name":"dude",
            "choices":[
                "yes (retaliate)",
                "no (swim off)"
            ],
            "content":"<div class=\"\"><div> <span>Having successfully learned Haki, you decide that it would be fun to mess with some boats. Spotting one on the surface above you, you notice that its a little larger than the one's you see normally. Moving closer to it, you notice that for a ship its huge, about as long as your head is wide. Knowing that this is white beards ship you decide to see how good they are. <br>\r\n<br>\r\nMore like jump scare but whatever.<br>\r\n<br>\r\nDiving back down then quickly swimming back up, you propel yourself pout of the water, managing to get about a fourth of your massive girth above the water, and quickly hear the white beard crew screaming down below, White Beard himself looking up with a bit of worry that you might hit his boat. Deciding to continue to screw with them, you duck back underwater before breaching on the other side of their ship. Curious to see what their next action might be, you decide just to tower above them, using your tail to lift them slightly out of the water, halting all movement.<br>\r\n<br>\r\nDoes white beard attack?</span></div></div>",
            "created":1607502300,
            "id":2954108,
            "title":"time skip one year"
        },
        "135":{
            "author_id":"tarandgreg",
            "author_name":"dude",
            "choices":[
                "High school DXD",
                "High school of the dead",
                "other"
            ],
            "content":"<div class=\"\"><span style=\"font-size:1.47em;\"><div> <span>How about High School _____</span></div></span></div>",
            "created":1607497920,
            "id":2954075,
            "title":"other"
        },
        "14":{
            "author_id":"tarandgreg",
            "author_name":"dude",
            "choices":[
                "PC",
                "Nintendo",
                "Xbox",
                "Play station",
                "other"
            ],
            "content":"<div class=\"\"><span style=\"font-size:1.47em;\"><div> <span>What platform<br>\r\n<br>\r\nPC<br>\r\n<br>\r\nNintendo<br>\r\n<br>\r\nXbox<br>\r\n<br>\r\nPlay station<br>\r\n<br>\r\nother</span></div></span></div>",
            "created":1607498100,
            "id":2954076,
            "title":"video game character"
        },
        "141":{
            "author_id":"tarandgreg",
            "author_name":"dude",
            "choices":[
                "overwatch",
                "SWTOR",
                "other"
            ],
            "content":"<div class=\"\"><span style=\"font-size:1.47em;\"><div> <span>How about Overwatch or Starwars the old republic (SWTOR)</span></div></span></div>",
            "created":1607503500,
            "id":2954122,
            "title":"PC"
        },
        "142":{
            "author_id":"tarandgreg",
            "author_name":"dude",
            "choices":[
                "male ",
                "female",
                "animal"
            ],
            "content":"<div class=\"\"><span style=\"font-size:1.47em;\"><div> <span>(Keep choices limited to characters found on Mario cart and Smash Bros any edition)</span></div></span></div>",
            "created":1607498400,
            "id":2954079,
            "title":"Nintendo"
        },
        "1422":{
            "author_id":"tarandgreg",
            "author_name":"dude",
            "choices":[
                "Samus",
                "Peach",
                "other"
            ],
            "content":"<div class=\"\"><span style=\"font-size:1.47em;\"><div> <span>Deciding that being a male loner for eighteen plus years is more than long enough, You decide to try the fairer side of life. Scrolling through the options in the character select screen of Mario Cart/Smash Bros, you finally decide on ______</span></div></span></div>",
            "created":1607498580,
            "id":2954080,
            "title":"female"
        },
        "14223":{
            "author_id":"tarandgreg",
            "author_name":"dude",
            "choices":[
                "zelda",
                "rosalina",
                "other"
            ],
            "content":"<div class=\"\"><span style=\"font-size:1.47em;\"><div> <span>If not the two most obvious choices then who</span></div></span></div>",
            "created":1607498580,
            "id":2954081,
            "title":"other"
        }
    },
    "info":{
        "author_id":"tarandgreg",
        "author_name":"dude",
        "brief_description":"Swap lives with fictional characters",
        "created":1607496900,
        "description":"<td align=\"left\" class=\"norm\">Everything but scat allowed<br>\r\nDo not kill characters</td>",
        "id":2239345,
        "image_url":"https://images.Writing.Com/imgs/writing.com/writers/listing-header-5000.gif",
        "last_full_update":1607503500,
        "modified":1607503500,
        "pretty_title":"Fictional body swap"
    }
}