{
    "chapters":{
        "1":{
            "author_id":"model7",
            "author_name":"Gojira6",
            "choices":[
                "In a House",
                "Somewhere Dark",
                "A Forest",
                "A Farm",
                "Somewhere else"
            ],
            "content":"<div class=\"\"><div> <span> \u00a0 \u00a0 \u00a0 \u00a0 \u00a0Briana White was relaxing on her couch playing her Nintendo switch. She wore a greyish t-shirt, blue jean shorts that left little to the imagination and was completely bare foot.Briana played her game for about half an hour when an odd message appear on her screen.<br>\r\n<br>\r\n \u00a0 \u00a0 \u00a0 \u00a0 \u00a0\"Click here to play the ultimate game?\" the young voice actress read out loud in confusion.<br>\r\n<br>\r\n \u00a0 \u00a0 \u00a0 \u00a0 \u00a0Then a smile appeared on her face. Perhaps Nintendo was somehow sending her invitation to test some new game. Without hesitation Briana clicked on the message. Suddenly, there was a blinding light and Briana cried out in shock.<br>\r\n<br>\r\n \u00a0 \u00a0 \u00a0 \u00a0 \u00a0When the light faded Briana blinked as her eyes readjusted. Then she screamed as she saw that she was no longer in her home and everything was gigantic. Judging by her surroundings the young voice actress appeared to somehow have been shrunk to about an inch in height. But where was Briana?</span></div></div>",
            "created":1569891360,
            "id":2726096,
            "title":"Briana White Shrinks"
        },
        "13":{
            "author_id":"kaijufanforeve",
            "author_name":"KaijuFanForever",
            "choices":[
                "Bat",
                "Possum",
                "Chipmunk",
                "Skunk",
                "more"
            ],
            "content":"<div class=\"\"><span style=\"font-size:1.47em;\"><div> <span>Briana found herself in the forest. Birds chirped as she looked about. She was a little nervous, for anything could eat her. Hearing a noise behind her, she spun to see a...</span></div></span></div>",
            "created":1591648320,
            "id":2848207,
            "title":"A Forest"
        },
        "15":{
            "author_id":"model7",
            "author_name":"Gojira6",
            "choices":[
                "A Beach",
                "The Zoo",
                "A Pet Store",
                "A Swamp",
                "Somewhere else still"
            ],
            "content":"<div class=\"\"><span style=\"font-size:1.47em;\"><div> <span>How about these locations?</span></div></span></div>",
            "created":1569891480,
            "id":2726097,
            "title":"Somewhere else"
        },
        "152":{
            "author_id":"kaijufanforeve",
            "author_name":"KaijuFanForever",
            "choices":[
                "Mammels",
                "Reptiles",
                "Birds"
            ],
            "content":"<div class=\"\"><span style=\"font-size:1.47em;\"><div> <span>Briana found herself in the Zoo. She looked about, wondering where to go. She look up at the mad, wondering where to start</span></div></span></div>",
            "created":1591554780,
            "id":2847506,
            "title":"The Zoo"
        },
        "1521":{
            "author_id":"kaijufanforeve",
            "author_name":"KaijuFanForever",
            "choices":[
                "large",
                "medium",
                "small"
            ],
            "content":"<div class=\"\"><span style=\"font-size:1.47em;\"><div> <span>which sized mammals will eat you?</span></div></span></div>",
            "created":1592265900,
            "id":2851829,
            "title":"Mammals"
        }
    },
    "info":{
        "author_id":"model7",
        "author_name":"Gojira6",
        "brief_description":"Briana White shrinks and will soon be eaten.",
        "created":1562883000,
        "description":"<td align=\"left\" class=\"norm\">Briana White mysteriously shrinks down to an inch in size. To make matters worse she now finds herself at the bottom of the food chain. How long can she survive before before she winds up in a belly?<br>\r\n<br>\r\nBriana White as she appears in this story: <a class=\"blue2roll\" rel=\"nofollow\" href=\"https://pics.wikifeet.com/Briana-White-Feet-3057722.jpg\" target=\"_blank\">https://pics.wikifeet.com/Briana-White-Feet-3057722.jpg</a><br>\r\n<br>\r\nRules:<br>\r\n1.) Briana can not grow or shrink more<br>\r\n2.) Briana is not immune to digestion<br>\r\n3.) All story lines must eventually end with Briana being eaten<br>\r\n4.) Humans must be mostly unaware of Briana at her new size<br>\r\n5.) Any human who notices Briana must either think she is a bug or be willing to treat her as food.<br>\r\n6.) Soft and cock vore only<br>\r\n7.) Have Fun<br>\r\n8.) No Dead ending the story.</td>",
        "id":2195504,
        "image_url":"https://images.Writing.Com/imgs/writing.com/writers/listing-header-5000.gif",
        "last_full_update":1592265900,
        "modified":1592265900,
        "pretty_title":"Briana White Shrunk and a Snack"
    }
}