{
    "chapters":{
        "1":{
            "author_id":"tyrakk",
            "author_name":"tyrak",
            "choices":[
                "Wakes up with nothing different",
                "Wakes up a little chubbier",
                "Wakes up huge"
            ],
            "content":"<div class=\"\"><div> <span>'Oh Tommy, you don't have to keep doing this' said Sarah as she helped her boyfriend out of the trash can. <br>\r\n<br>\r\nTommy was sweat, but a pretty skinny kid. He had tried to stand up for his girlfriend against some jock, but it didn't go well.<br>\r\n<br>\r\n'He never learns' commented his younger sister Elisa, Sarah's friend.<br>\r\n<br>\r\n***<br>\r\n<br>\r\nI'll show them, Tommy thought. He had ordered some weight-gain pills to buff him up, so he could impress Sarah.<br>\r\n<br>\r\nAs it takes four, he dosen't notice a warning label on the bottle...</span></div></div>",
            "created":1184978340,
            "id":427689,
            "title":"The beginning"
        },
        "11":{
            "author_id":"tyrakk",
            "author_name":"tyrak",
            "choices":[
                "Go to school",
                "Go eat breakfast",
                "His sister walks in"
            ],
            "content":"<div class=\"\"><span style=\"font-size:1.47em;\"><div> <span>He woke up the next morning, and to his dissapointment, no muscles have developed.<br>\r\n<br>\r\n'I guess it takes time' he mused.</span></div></span></div>",
            "created":1184985180,
            "id":427715,
            "title":"Guess it takes time"
        },
        "113":{
            "author_id":"tyrakk",
            "author_name":"tyrak",
            "choices":[
                "She does",
                "She does not"
            ],
            "content":"<div class=\"\"><div> <span>Then, Elisa walks in.<br>\r\n<br>\r\n'What, making sure you still skinny?' she quipped.<br>\r\n<br>\r\n'Shut up'<br>\r\n<br>\r\nShe then saw the bottle.<br>\r\n<br>\r\n'Pills? These never work'<br>\r\n<br>\r\n'Listen, just leave!'</span></div></div>",
            "created":1184985420,
            "id":427717,
            "title":"Sister shows up"
        },
        "1132":{
            "author_id":"batboyjw",
            "author_name":"Jokermask18",
            "choices":[
                "His rage make his muscles grow. He then challenges his sister to a fight.",
                "He challenges his sister to a fight She beats him up.",
                "He takes more pills."
            ],
            "content":"<div class=\"\"><span style=\"font-size:1.47em;\"><div> <span>\"Make me, wimpo! Take another magic pill and beat me up with your big muscles.\" Tommy got mad at his sister's taunt and began to growl in rage.</span></div></span></div>",
            "created":1542345000,
            "id":2578449,
            "title":"She does not"
        },
        "12":{
            "author_id":"tyrakk",
            "author_name":"tyrak",
            "choices":[
                "Check more",
                "Ignore it",
                "Sister notices, makes fun of him",
                "Girlfriend notices."
            ],
            "content":"<div class=\"\"><span style=\"font-size:1.47em;\"><div> <span>Tommy eagerly inspected himself in the mirror the next morning. To his dissapointment, he did not look buffer. <br>\r\n<br>\r\nAs he turned around, he noticed a little sway to his butt. He looked at it. Was it bigger...?</span></div></span></div>",
            "created":1187660460,
            "id":437597,
            "title":"Bigger Butt"
        },
        "121":{
            "author_id":"archerman",
            "author_name":"d",
            "choices":[
                "What are you doing?",
                "Have you gained weight?"
            ],
            "content":"<div class=\"\"><div> <span>                <br>\r\n                 Tommy next lifts up his shirt....to his surprise a small mound of flesh has gathered around his waist. <br>\r\n<br>\r\n           Just as he puts his shirt down his sister walks in and say\"***************\".</span></div></div>",
            "created":1188844980,
            "id":441828,
            "title":"Little Tummy"
        },
        "1212":{
            "author_id":"johnjackjohnny",
            "author_name":"Dreemurr",
            "choices":[
                "Yes",
                "No",
                "Something else"
            ],
            "content":"<div class=\"\"><span style=\"font-size:1.47em;\"><div> <span>Does he tell the truth</span></div></span></div>",
            "created":1465782900,
            "id":2163266,
            "title":"Have you gained weight?"
        },
        "12123":{
            "author_id":"johnjackjohnny",
            "author_name":"Dreemurr",
            "choices":[
                "His sister helps him",
                "Something else"
            ],
            "content":"<div class=\"\"><div> <span>Huh, I suspected what happened might cause you to do something like this<br>\r\n<br>\r\nWhat do you mean?<br>\r\n<br>\r\nThe fight you know how you lost remember<br>\r\n<br>\r\nOh right<br>\r\n<br>\r\nLooks like it backfired<br>\r\n<br>\r\nYeah I dint read it very well</span></div></div>",
            "created":1465783260,
            "id":2163272,
            "title":"Something else"
        },
        "123":{
            "author_id":"johnjackjohnny",
            "author_name":"Dreemurr",
            "choices":[
                "Sure",
                "Hell no"
            ],
            "content":"<div class=\"\"><div> <span>Hey, I was just wandering if...<br>\r\n(Dead silence)<br>\r\nWhat the f*ck happened <br>\r\nUh I was no had woke up like this<br>\r\nWow it's just so huge like a girls <br>\r\nHey be quiet <br>\r\nNo sorry just it's really big I mean if I were someone else i totally would've squeezed it and kissed <br>\r\nI mean if your ok I am</span></div></div>",
            "created":1465784100,
            "id":2163277,
            "title":"Sister notices, makes fun of him"
        },
        "1231":{
            "author_id":"johnjackjohnny",
            "author_name":"Dreemurr",
            "choices":[
                "Can you help me",
                "Can you leave now",
                "Why did you come in here"
            ],
            "content":"<div class=\"\"><span style=\"font-size:1.47em;\"><div> <span>No im just kidding gross yeah me too <br>\r\n(His face looks like he meant it)</span></div></span></div>",
            "created":1465784880,
            "id":2163283,
            "title":"Sure"
        }
    },
    "info":{
        "author_id":"tyrakk",
        "author_name":"tyrak",
        "brief_description":"90-pound weakling takes pills to get buffed up, but doesn't read a warning label carefully",
        "created":1184978040,
        "description":"<td align=\"left\" class=\"norm\">Tommy takes pills to muscle up, but has some unforseen side-effects...</td>",
        "id":1294483,
        "image_url":"https://images.Writing.Com/imgs/writing.com/writers/listing-header-5000.gif",
        "last_full_update":1542345000,
        "modified":1542345000,
        "pretty_title":"Weight Trouble"
    }
}